{
   "leaderboards":[
      {
         "name":"consumption",
         "unit":"l/100km",
         "description":"minimum average fuel consumption",
         "created":"2013-10-04T13:36:12Z",
         "modified":"2014-07-09T08:59:56Z",
         "rankings":[
            {
               "name":"Pete",
               "value":3.846
            },
            {
               "name":"rsh1103",
               "value":3.941
            },
            {
               "name":"Tosin",
               "value":3.992
            },
            {
               "name":"Frank",
               "value":4.163
            },
            {
               "name":"Marvin",
               "value":4.238
            }
         ]
      },
      {
         "name":"co2Emissions",
         "unit":"kg/h",
         "description":"minimum CO2 emissions",
         "created":"2013-10-04T13:36:12Z",
         "modified":"2014-07-09T08:59:56Z",
         "rankings":[
            {
               "name":"Pete",
               "value":7.846
            },
            {
               "name":"Jenn",
               "value":8.941
            },
            {
               "name":"Tosin",
               "value":8.992
            },
            {
               "name":"rsh1103",
               "value":9.163
            },
            {
               "name":"Marvin",
               "value":12.238
            }
         ]
      }
   ]
}
